README.md
setup.py
src/vdk/plugin/ingest_http/ingest_http_plugin.py
src/vdk/plugin/ingest_http/ingest_over_http.py
src/vdk_ingest_http.egg-info/PKG-INFO
src/vdk_ingest_http.egg-info/SOURCES.txt
src/vdk_ingest_http.egg-info/dependency_links.txt
src/vdk_ingest_http.egg-info/entry_points.txt
src/vdk_ingest_http.egg-info/requires.txt
src/vdk_ingest_http.egg-info/top_level.txt
tests/test_ingest_over_http.py